MANIFEST.in
README.rst
requirements.txt
setup.cfg
setup.py
djmicrosip_faexist/__init__.py
djmicrosip_faexist/__init__.pyc
djmicrosip_faexist/autocomplete_light_registry.pyc
djmicrosip_faexist/config.pyc
djmicrosip_faexist/forms.pyc
djmicrosip_faexist/models.pyc
djmicrosip_faexist/procedures.pyc
djmicrosip_faexist/urls.pyc
djmicrosip_faexist/views.pyc
djmicrosip_faexist.egg-info/PKG-INFO
djmicrosip_faexist.egg-info/SOURCES.txt
djmicrosip_faexist.egg-info/dependency_links.txt
djmicrosip_faexist.egg-info/requires.txt
djmicrosip_faexist.egg-info/top_level.txt
djmicrosip_faexist/static/djmicrosip_faexist/js/articulos.js
djmicrosip_faexist/static/djmicrosip_faexist/js/generarCompras.js
djmicrosip_faexist/static/djmicrosip_faexist/js/generarVenta.js
djmicrosip_faexist/static/djmicrosip_faexist/js/main.js
djmicrosip_faexist/templates/djmicrosip_faexist/base.html
djmicrosip_faexist/templates/djmicrosip_faexist/exporta_factura.html
djmicrosip_faexist/templates/djmicrosip_faexist/index.html
djmicrosip_faexist/templates/djmicrosip_faexist/preferencias.html
djmicrosip_faexist/templates/djmicrosip_faexist/articulos/articulo.html
djmicrosip_faexist/templates/djmicrosip_faexist/articulos/articulos.html